RandomWiFi/FreeWiFi.py
RandomWiFi/__init__.py
RandomWiFi-3.8.5.1.dist-info/METADATA
RandomWiFi-3.8.5.1.dist-info/WHEEL
RandomWiFi-3.8.5.1.dist-info/top_level.txt
RandomWiFi-3.8.5.1.dist-info/RECORD
